quickEncrypt/__init__.py
quickEncrypt/core.py
quickencr-0.1.1.dist-info/METADATA
quickencr-0.1.1.dist-info/WHEEL
quickencr-0.1.1.dist-info/top_level.txt
quickencr-0.1.1.dist-info/RECORD
